leaf/__init__.py
leaf-1.0.7.dist-info/AUTHORS.md
leaf-1.0.7.dist-info/LICENSE.md
leaf-1.0.7.dist-info/METADATA
leaf-1.0.7.dist-info/WHEEL
leaf-1.0.7.dist-info/top_level.txt
leaf-1.0.7.dist-info/RECORD
