Metadata-Version: 2.1
Name: leaf
Version: 1.0.7
Summary: Simple Python library for HTML parsing
Home-page: https://github.com/penpen/leaf
Author: Roman Koblov
Author-email: hello@romankoblov.com
License: MIT
Keywords: html,parsing,web scrapping
Platform: UNKNOWN
Classifier: Development Status :: 5 - Production/Stable
Classifier: Intended Audience :: Developers
Classifier: License :: OSI Approved :: MIT License
Classifier: Operating System :: OS Independent
Classifier: Programming Language :: Python
Classifier: Programming Language :: Python :: 2.7
Classifier: Programming Language :: Python :: 3
Classifier: Programming Language :: Python :: 3.7
Classifier: Topic :: Scientific/Engineering :: Information Analysis
Requires-Dist: setuptools
Requires-Dist: lxml
Requires-Dist: cssselect
Requires-Dist: six
